FlockMP-1.2.0b7.dist-info/DESCRIPTION.rst
FlockMP-1.2.0b7.dist-info/METADATA
FlockMP-1.2.0b7.dist-info/RECORD
FlockMP-1.2.0b7.dist-info/WHEEL
FlockMP-1.2.0b7.dist-info/metadata.json
FlockMP-1.2.0b7.dist-info/top_level.txt
flockmp/__init__.py
flockmp/errors.py
flockmp/tools.py
flockmp/base/__init__.py
flockmp/database/__init__.py
flockmp/database/setup.py
flockmp/dataframe/__init__.py
flockmp/list/__init__.py
flockmp/utils/__init__.py
flockmp/utils/logger.py
