Metadata-Version: 2.0
Name: FlockMP
Version: 1.2.0b7
Summary: Python duck-like multiprocessing library
Home-page: https://github.com/Captalys/flock
Author: Wanderson Ferreira & Denis Urbanavicius
Author-email: wanderson.ferreira@captalys.com.br
License: MIT
Keywords: captalys analitics multiprocessing dataframe
Platform: UNKNOWN
Classifier: Development Status :: 4 - Beta
Classifier: Intended Audience :: Developers
Classifier: Topic :: Software Development :: Build Tools
Classifier: License :: OSI Approved :: MIT License
Classifier: Programming Language :: Python :: 3
Classifier: Programming Language :: Python :: 3.2
Classifier: Programming Language :: Python :: 3.3
Classifier: Programming Language :: Python :: 3.4
Requires-Python: >=3
Requires-Dist: dill
Requires-Dist: pandas
Requires-Dist: numpy
Requires-Dist: tqdm
